[
  {
    "id": "eccfeb61eb813ea8b17daf7144e2562c",
    "name": "fm1._domainkey.nathanbaxter.com",
    "type": "CNAME",
    "content": "fm1.nathanbaxter.com.dkim.fmhosted.com",
    "proxiable": true,
    "proxied": false,
    "ttl": 1,
    "settings": {
      "flatten_cname": false
    },
    "meta": {},
    "comment": null,
    "tags": [],
    "created_on": "2021-04-21T05:44:28.789363Z",
    "modified_on": "2021-04-21T05:44:28.789363Z"
  },
  {
    "id": "726c6934b42390fd7f471a816e8936c5",
    "name": "fm2._domainkey.nathanbaxter.com",
    "type": "CNAME",
    "content": "fm2.nathanbaxter.com.dkim.fmhosted.com",
    "proxiable": true,
    "proxied": false,
    "ttl": 1,
    "settings": {
      "flatten_cname": false
    },
    "meta": {},
    "comment": null,
    "tags": [],
    "created_on": "2021-04-21T05:44:36.707864Z",
    "modified_on": "2021-04-21T05:44:36.707864Z"
  },
  {
    "id": "9b66daa17026b6e313e8c30f9ee45f27",
    "name": "fm3._domainkey.nathanbaxter.com",
    "type": "CNAME",
    "content": "fm3.nathanbaxter.com.dkim.fmhosted.com",
    "proxiable": true,
    "proxied": false,
    "ttl": 1,
    "settings": {
      "flatten_cname": false
    },
    "meta": {},
    "comment": null,
    "tags": [],
    "created_on": "2021-04-21T05:44:45.902848Z",
    "modified_on": "2021-04-21T05:44:45.902848Z"
  },
  {
    "id": "7018a4c10a41315efb1d763ed30b53f3",
    "name": "mail.nathanbaxter.com",
    "type": "CNAME",
    "content": "app.fastmail.com",
    "proxiable": true,
    "proxied": true,
    "ttl": 1,
    "settings": {
      "flatten_cname": false
    },
    "meta": {},
    "comment": null,
    "tags": [],
    "created_on": "2021-02-16T08:11:36.81731Z",
    "modified_on": "2024-10-15T01:53:10.203788Z"
  },
  {
    "id": "7cb639937631a4764fdb67ec6c97b8dc",
    "name": "pm-bounces.nathanbaxter.com",
    "type": "CNAME",
    "content": "pm.mtasv.net",
    "proxiable": true,
    "proxied": false,
    "ttl": 1,
    "settings": {
      "flatten_cname": false
    },
    "meta": {},
    "comment": null,
    "tags": [],
    "created_on": "2025-10-19T03:06:52.556678Z",
    "modified_on": "2025-10-19T03:06:52.556678Z"
  },
  {
    "id": "aa10904f0e780b3fa0c1d047aea04d6d",
    "name": "*.nathanbaxter.com",
    "type": "MX",
    "content": "in2-smtp.messagingengine.com",
    "priority": 20,
    "proxiable": false,
    "proxied": false,
    "ttl": 1,
    "settings": {},
    "meta": {},
    "comment": null,
    "tags": [],
    "created_on": "2021-02-08T07:58:42.467537Z",
    "modified_on": "2021-02-08T07:58:42.467537Z"
  },
  {
    "id": "7e73e5ec990ee946235a4da3f8351cf3",
    "name": "*.nathanbaxter.com",
    "type": "MX",
    "content": "in1-smtp.messagingengine.com",
    "priority": 10,
    "proxiable": false,
    "proxied": false,
    "ttl": 1,
    "settings": {},
    "meta": {},
    "comment": null,
    "tags": [],
    "created_on": "2021-02-08T07:58:42.464438Z",
    "modified_on": "2021-02-08T07:58:42.464438Z"
  },
  {
    "id": "00dcbd4fdddb5f65eb7332016c81ce1f",
    "name": "nathanbaxter.com",
    "type": "MX",
    "content": "in2-smtp.messagingengine.com",
    "priority": 20,
    "proxiable": false,
    "proxied": false,
    "ttl": 1,
    "settings": {},
    "meta": {},
    "comment": null,
    "tags": [],
    "created_on": "2021-02-08T07:58:42.439066Z",
    "modified_on": "2021-02-08T07:58:42.439066Z"
  },
  {
    "id": "2b17a50a787f75b1b12aad3972cb15dd",
    "name": "nathanbaxter.com",
    "type": "MX",
    "content": "in1-smtp.messagingengine.com",
    "priority": 10,
    "proxiable": false,
    "proxied": false,
    "ttl": 1,
    "settings": {},
    "meta": {},
    "comment": null,
    "tags": [],
    "created_on": "2021-02-08T07:58:42.435297Z",
    "modified_on": "2021-02-08T07:58:42.435297Z"
  },
  {
    "id": "0ca9e31cdba6e09752f49f8068ecc492",
    "name": "www.nathanbaxter.com",
    "type": "MX",
    "content": "in2-smtp.messagingengine.com",
    "priority": 20,
    "proxiable": false,
    "proxied": false,
    "ttl": 1,
    "settings": {},
    "meta": {},
    "comment": null,
    "tags": [],
    "created_on": "2021-02-08T07:58:42.475242Z",
    "modified_on": "2021-02-08T07:58:42.475242Z"
  },
  {
    "id": "5c59be2cb2804ae39ed5e15dd845f1dd",
    "name": "www.nathanbaxter.com",
    "type": "MX",
    "content": "in1-smtp.messagingengine.com",
    "priority": 10,
    "proxiable": false,
    "proxied": false,
    "ttl": 1,
    "settings": {},
    "meta": {},
    "comment": null,
    "tags": [],
    "created_on": "2021-02-08T07:58:42.472448Z",
    "modified_on": "2021-02-08T07:58:42.472448Z"
  },
  {
    "id": "ceb682d25c9d7c097cbed6de625b4d99",
    "name": "_caldavs._tcp.nathanbaxter.com",
    "type": "SRV",
    "content": "1 443 caldav.fastmail.com",
    "priority": 0,
    "proxiable": false,
    "proxied": false,
    "ttl": 1,
    "data": {
      "port": 443,
      "priority": 0,
      "target": "caldav.fastmail.com",
      "weight": 1
    },
    "settings": {},
    "meta": {},
    "comment": null,
    "tags": [],
    "created_on": "2021-02-08T07:58:42.455669Z",
    "modified_on": "2021-02-08T07:58:42.455669Z"
  },
  {
    "id": "55c2709b4960ae090684ef438a370d3d",
    "name": "_carddavs._tcp.nathanbaxter.com",
    "type": "SRV",
    "content": "1 443 carddav.fastmail.com",
    "priority": 0,
    "proxiable": false,
    "proxied": false,
    "ttl": 1,
    "data": {
      "port": 443,
      "priority": 0,
      "target": "carddav.fastmail.com",
      "weight": 1
    },
    "settings": {},
    "meta": {},
    "comment": null,
    "tags": [],
    "created_on": "2021-02-08T07:58:42.452094Z",
    "modified_on": "2021-02-08T07:58:42.452094Z"
  },
  {
    "id": "6ba66ee518a442fbb5d50a4cee87cf66",
    "name": "_imaps._tcp.nathanbaxter.com",
    "type": "SRV",
    "content": "1 993 imap.fastmail.com",
    "priority": 0,
    "proxiable": false,
    "proxied": false,
    "ttl": 1,
    "data": {
      "port": 993,
      "priority": 0,
      "target": "imap.fastmail.com",
      "weight": 1
    },
    "settings": {},
    "meta": {},
    "comment": null,
    "tags": [],
    "created_on": "2021-02-08T07:58:42.480918Z",
    "modified_on": "2021-02-08T07:58:42.480918Z"
  },
  {
    "id": "d2579903b2715820ecce12589b127fb5",
    "name": "_pop3s._tcp.nathanbaxter.com",
    "type": "SRV",
    "content": "1 995 pop.fastmail.com",
    "priority": 10,
    "proxiable": false,
    "proxied": false,
    "ttl": 1,
    "data": {
      "port": 995,
      "priority": 10,
      "target": "pop.fastmail.com",
      "weight": 1
    },
    "settings": {},
    "meta": {},
    "comment": null,
    "tags": [],
    "created_on": "2021-02-08T07:58:42.493261Z",
    "modified_on": "2021-02-08T07:58:42.493261Z"
  },
  {
    "id": "80a103555134a1f35073b2afe355e029",
    "name": "_submission._tcp.nathanbaxter.com",
    "type": "SRV",
    "content": "1 587 smtp.fastmail.com",
    "priority": 0,
    "proxiable": false,
    "proxied": false,
    "ttl": 1,
    "data": {
      "port": 587,
      "priority": 0,
      "target": "smtp.fastmail.com",
      "weight": 1
    },
    "settings": {},
    "meta": {},
    "comment": null,
    "tags": [],
    "created_on": "2021-02-08T07:58:42.478045Z",
    "modified_on": "2021-02-08T07:58:42.478045Z"
  },
  {
    "id": "72e47264474cb34e3cfcc464a097af4f",
    "name": "20251019030332pm._domainkey.nathanbaxter.com",
    "type": "TXT",
    "content": "\"k=rsa;p=MIGfMA0GCSqGSIb3DQEBAQUAA4GNADCBiQKBgQDYtsXWV3F5hNjZtbIHesrQ40jJ9fYiX/te3iiDt+6+dGHwjroZQDwGRg9hcEjRX/Ev1UTecR32/14Ie7zoD35OwiZ8c0/V5ojaB2CHtaWVHkzwINwKTCCcOOBbezHFsUvk7JPE7Il5U0weRbcLEcYOxyM1oEXxTrA+wlKS13JkaQIDAQAB\"",
    "proxiable": false,
    "proxied": false,
    "ttl": 1,
    "settings": {},
    "meta": {},
    "comment": null,
    "tags": [],
    "created_on": "2025-10-19T03:06:26.005986Z",
    "modified_on": "2025-10-19T03:06:26.005986Z"
  },
  {
    "id": "52ee457343a58f25b3ad2ce8ad18e1a9",
    "name": "mail.nathanbaxter.com",
    "type": "TXT",
    "content": "ALIAS for mail.fastmail.com",
    "proxiable": false,
    "proxied": false,
    "ttl": 1,
    "settings": {},
    "meta": {},
    "comment": null,
    "tags": [],
    "created_on": "2021-02-08T07:58:42.470003Z",
    "modified_on": "2021-02-08T07:58:42.470003Z"
  },
  {
    "id": "8a24ad792a62fc758322373dc270901f",
    "name": "nathanbaxter.com",
    "type": "TXT",
    "content": "v=spf1 include:spf.messagingengine.com ~all",
    "proxiable": false,
    "proxied": false,
    "ttl": 1,
    "settings": {},
    "meta": {},
    "comment": null,
    "tags": [],
    "created_on": "2021-02-08T07:58:42.449105Z",
    "modified_on": "2021-02-08T07:58:42.449105Z"
  },
  {
    "id": "64b15a5ef030f2fb599116030c271fce",
    "name": "nathanbaxter.com",
    "type": "TXT",
    "content": "keybase-site-verification=PYg39KGImTNyG3xYnl4VUNhzg51qNFmDhZyBDwLKO0A",
    "proxiable": false,
    "proxied": false,
    "ttl": 1,
    "settings": {},
    "meta": {},
    "comment": null,
    "tags": [],
    "created_on": "2021-02-08T07:58:42.445968Z",
    "modified_on": "2021-02-08T07:58:42.445968Z"
  }
]
